{
  "basicInfo": {
    "name": "Makkah Hotel",
    "cuisine_string": "North Indian, Mughlai",
    "canonicalUrl": "https://www.zomato.com/surat/makkah-hotel-katargam/order"
  },
  "ratings": {
    "DINING": {
      "rating_type": "DINING",
      "rating": "3.4",
      "reviewCount": "67",
      "reviewTextSmall": "67 Reviews",
      "subtext": "67 Dining Reviews",
      "color": "#1C1C1C",
      "ratingV2": "3.4",
      "subtitle": "DINING",
      "sideSubTitle": "Dining Ratings",
      "bgColorV2": {
        "type": "green",
        "tint": "500"
      },
      "newOnDining": false
    },
    "DELIVERY": {
      "rating_type": "DELIVERY",
      "rating": "3.8",
      "reviewCount": "3,225",
      "reviewTextSmall": "3,225 Reviews",
      "subtext": "3,225 Delivery Reviews",
      "color": "#E23744",
      "ratingV2": "3.8",
      "subtitle": "DELIVERY",
      "sideSubTitle": "Delivery Ratings",
      "bgColorV2": {
        "type": "green",
        "tint": "600"
      },
      "newOnDelivery": false
    }
  },
  "establishment": {
    "city_id": 38,
    "city_name": "Surat",
    "country_id": 1,
    "country_name": "India",
    "zipcode": "",
    "is_dark_kitchen": false,
    "locality_verbose": "Katargam, Surat",
    "latitude": "21.2096410000",
    "longitude": "72.8173350000",
    "static_map_url": "https://maps.zomato.com/php/staticmap?center=21.2096410000,72.8173350000&maptype=zomato&markers=21.2096410000,72.8173350000,pin_res32&sensor=false&scale=2&zoom=16&language=en&size=240x150&size=400x240",
    "address": "507, Rail Rahat Colony, Fulwadi, Bharimata Road, Near Madina Masjid, Katargam, Surat",
    "is_phone_available": 1,
    "phoneDetails": {
      "title": "Phone Numbers",
      "phoneStr": "+918488967407, +919586528896"
    },
    "res_chain_text": "",
    "res_group_text": "",
    "res_chain_url": "",
    "res_group_url": "",
    "show_res_map": true
  },
  "items": [
    {
      "name": "Paneer Tikka Masala [Half] + 6 Chapati Roti + Papad + Chhas",
      "description": "[Veg preparation]",
      "media": null,
      "price": 249,
      "menuName": "Zomato Special Combo",
      "categoryName": "",
      "slugs": [
        "veg",
        "combo-item",
        "zpl-combo",
        "home-style-meal",
        "services",
        "sf-not-vegan",
        "delivery-enabled",
        "delivery-enabled",
        "veg",
        "combo-item",
        "zpl-combo",
        "home-style-meal",
        "services",
        "sf-not-vegan",
        "veg"
      ]
    },
    {
      "name": "Paneer Masala [Half] + 4 Chapati Roti + Dal Rice [Half] + Papad + Chhas",
      "description": "",
      "media": null,
      "price": 269,
      "menuName": "Zomato Special Combo",
      "categoryName": "",
      "slugs": [
        "veg",
        "combo-item",
        "zpl-combo",
        "home-style-meal",
        "services",
        "sf-not-vegan",
        "delivery-enabled",
        "delivery-enabled",
        "veg",
        "combo-item",
        "zpl-combo",
        "home-style-meal",
        "services",
        "sf-not-vegan",
        "veg"
      ]
    },
    {
      "name": "Chicken Kadhai [Half] + 4 Butter Chapati Roti + Chicken Biryani [Half] + Papad + Masala Chhas",
      "description": "",
      "media": null,
      "price": 279,
      "menuName": "Zomato Special Combo",
      "categoryName": "",
      "slugs": [
        "non-veg",
        "restaurant-recommended",
        "combo-item",
        "zpl-combo",
        "home-style-meal",
        "services",
        "delivery-enabled",
        "delivery-enabled",
        "non-veg",
        "restaurant-recommended",
        "combo-item",
        "zpl-combo",
        "home-style-meal",
        "services",
        "non-veg"
      ]
    },
    {
      "name": "Chicken Green Masala [Half] + 4 Butter Chapati Roti + Chicken Biryani [Half] + 2 Papad + Masala Chhas",
      "description": "",
      "media": null,
      "price": 289,
      "menuName": "Zomato Special Combo",
      "categoryName": "",
      "slugs": [
        "non-veg",
        "restaurant-recommended",
        "combo-item",
        "zpl-combo",
        "home-style-meal",
        "services",
        "delivery-enabled",
        "delivery-enabled",
        "non-veg",
        "restaurant-recommended",
        "combo-item",
        "zpl-combo",
        "home-style-meal",
        "services",
        "non-veg"
      ]
    },
    {
      "name": "Chicken Hyderabadi [Half] + 4 Butter Chapati Roti + Dal + Rice + 2 Papad + Masala Chhas",
      "description": "",
      "media": null,
      "price": 289,
      "menuName": "Zomato Special Combo",
      "categoryName": "",
      "slugs": [
        "non-veg",
        "restaurant-recommended",
        "combo-item",
        "zpl-combo",
        "home-style-meal",
        "services",
        "delivery-enabled",
        "delivery-enabled",
        "non-veg",
        "restaurant-recommended",
        "combo-item",
        "zpl-combo",
        "home-style-meal",
        "services",
        "non-veg"
      ]
    },
    {
      "name": "Chicken Handi [Half] + 4 Chapati Roti + Dal + Rice + 2 Papad + Masala Chhas",
      "description": "",
      "media": null,
      "price": 299,
      "menuName": "Zomato Special Combo",
      "categoryName": "",
      "slugs": [
        "non-veg",
        "combo-item",
        "zpl-combo",
        "home-style-meal",
        "services",
        "delivery-enabled",
        "delivery-enabled",
        "non-veg",
        "combo-item",
        "zpl-combo",
        "home-style-meal",
        "services",
        "non-veg"
      ]
    },
    {
      "name": "Chicken Dana 65 [250 Grm] + Chicken Masala [Half] + 6 Chapati Roti + 2 Papad + Cold Drink",
      "description": "",
      "media": null,
      "price": 399,
      "menuName": "Zomato Special Combo",
      "categoryName": "",
      "slugs": [
        "non-veg",
        "combo-item",
        "zpl-combo",
        "home-style-meal",
        "services",
        "delivery-enabled",
        "delivery-enabled",
        "non-veg",
        "combo-item",
        "zpl-combo",
        "home-style-meal",
        "services",
        "non-veg"
      ]
    },
    {
      "name": "Chicken Tandoori Leg [1 Pc] + Chicken Hyderabadi [Half] + 6 Chapati Roti + Dal + Rice + 2 Papad + 2 Masala Chhas",
      "description": "",
      "media": null,
      "price": 439,
      "menuName": "Zomato Special Combo",
      "categoryName": "",
      "slugs": [
        "non-veg",
        "combo-item",
        "zpl-combo",
        "home-style-meal",
        "services",
        "delivery-enabled",
        "delivery-enabled",
        "non-veg",
        "combo-item",
        "zpl-combo",
        "home-style-meal",
        "services",
        "non-veg"
      ]
    },
    {
      "name": "Chicken Tandoori Leg",
      "description": "",
      "media": "https://b.zmtcdn.com/data/dish_photos/944/34d6840c7af3861cc07ccae1e97a9944.jpg",
      "price": 150,
      "menuName": "Starters",
      "categoryName": "Chicken Dries",
      "slugs": [
        "non-veg",
        "reco-snacks",
        "bestseller-lunch",
        "bestseller-evening",
        "bestseller-dinner",
        "bestseller-late-night",
        "hero-item",
        "services",
        "delivery-enabled",
        "delivery-enabled",
        "non-veg",
        "reco-snacks",
        "bestseller-lunch",
        "bestseller-evening",
        "bestseller-dinner",
        "bestseller-late-night",
        "hero-item",
        "services",
        "non-veg"
      ]
    },
    {
      "name": "Chicken Tandoori Chest",
      "description": "",
      "media": null,
      "price": 150,
      "menuName": "Starters",
      "categoryName": "Chicken Dries",
      "slugs": [
        "non-veg",
        "reco-snacks",
        "bestseller-dinner",
        "services",
        "delivery-enabled",
        "delivery-enabled",
        "non-veg",
        "reco-snacks",
        "bestseller-dinner",
        "services",
        "non-veg"
      ]
    },
    {
      "name": "Chicken Daana 65",
      "description": "",
      "media": "https://b.zmtcdn.com/data/dish_photos/40a/56de51701e01aa997617c6484123140a.jpg",
      "price": 150,
      "menuName": "Starters",
      "categoryName": "Chicken Dries",
      "slugs": [
        "non-veg",
        "reco-snacks",
        "restaurant-recommended",
        "hero-item",
        "services",
        "delivery-enabled",
        "delivery-enabled",
        "non-veg",
        "reco-snacks",
        "restaurant-recommended",
        "hero-item",
        "services",
        "non-veg"
      ]
    },
    {
      "name": "Paneer Masala",
      "description": "",
      "media": null,
      "price": 160,
      "menuName": "Main Course",
      "categoryName": "Veg Main Course",
      "slugs": [
        "veg",
        "pair-with-bread",
        "services",
        "sf-not-vegan",
        "delivery-enabled",
        "delivery-enabled",
        "veg",
        "pair-with-bread",
        "services",
        "sf-not-vegan",
        "veg"
      ]
    },
    {
      "name": "Paneer Palak",
      "description": "",
      "media": null,
      "price": 170,
      "menuName": "Main Course",
      "categoryName": "Veg Main Course",
      "slugs": [
        "veg",
        "services",
        "sf-not-vegan",
        "delivery-enabled",
        "delivery-enabled",
        "veg",
        "services",
        "sf-not-vegan",
        "veg"
      ]
    },
    {
      "name": "Paneer Bhurji",
      "description": "",
      "media": null,
      "price": 160,
      "menuName": "Main Course",
      "categoryName": "Veg Main Course",
      "slugs": [
        "veg",
        "services",
        "sf-not-vegan",
        "delivery-enabled",
        "delivery-enabled",
        "veg",
        "services",
        "sf-not-vegan",
        "veg"
      ]
    },
    {
      "name": "Paneer Kadai",
      "description": "",
      "media": null,
      "price": 190,
      "menuName": "Main Course",
      "categoryName": "Veg Main Course",
      "slugs": [
        "veg",
        "bestseller-evening",
        "services",
        "sf-not-vegan",
        "delivery-enabled",
        "delivery-enabled",
        "veg",
        "bestseller-evening",
        "services",
        "sf-not-vegan",
        "veg"
      ]
    },
    {
      "name": "Shahi Paneer",
      "description": "",
      "media": null,
      "price": 190,
      "menuName": "Main Course",
      "categoryName": "Veg Main Course",
      "slugs": [
        "veg",
        "bestseller-evening",
        "pair-with-bread",
        "services",
        "sf-not-vegan",
        "delivery-enabled",
        "delivery-enabled",
        "veg",
        "bestseller-evening",
        "pair-with-bread",
        "services",
        "sf-not-vegan",
        "veg"
      ]
    },
    {
      "name": "Chana Paneer",
      "description": "",
      "media": null,
      "price": 180,
      "menuName": "Main Course",
      "categoryName": "Veg Main Course",
      "slugs": [
        "veg",
        "bestseller-late-night",
        "services",
        "sf-not-vegan",
        "delivery-enabled",
        "delivery-enabled",
        "veg",
        "bestseller-late-night",
        "services",
        "sf-not-vegan",
        "veg"
      ]
    },
    {
      "name": "Paneer Handi",
      "description": "",
      "media": null,
      "price": 190,
      "menuName": "Main Course",
      "categoryName": "Veg Main Course",
      "slugs": [
        "veg",
        "services",
        "sf-not-vegan",
        "delivery-enabled",
        "delivery-enabled",
        "veg",
        "services",
        "sf-not-vegan",
        "veg"
      ]
    },
    {
      "name": "Paneer Tikka Masala",
      "description": "",
      "media": null,
      "price": 200,
      "menuName": "Main Course",
      "categoryName": "Veg Main Course",
      "slugs": [
        "veg",
        "bestseller-lunch",
        "pair-with-bread",
        "services",
        "sf-not-vegan",
        "delivery-enabled",
        "delivery-enabled",
        "veg",
        "bestseller-lunch",
        "pair-with-bread",
        "services",
        "sf-not-vegan",
        "veg"
      ]
    },
    {
      "name": "Aloo Gobi",
      "description": "",
      "media": null,
      "price": 80,
      "menuName": "Main Course",
      "categoryName": "Veg Main Course",
      "slugs": [
        "veg",
        "bestseller-dinner",
        "pair-with-bread",
        "home-style-meal",
        "services",
        "delivery-enabled",
        "delivery-enabled",
        "veg",
        "bestseller-dinner",
        "pair-with-bread",
        "home-style-meal",
        "services",
        "veg"
      ]
    },
    {
      "name": "Aloo Palak",
      "description": "",
      "media": null,
      "price": 90,
      "menuName": "Main Course",
      "categoryName": "Veg Main Course",
      "slugs": [
        "veg",
        "pair-with-bread",
        "home-style-meal",
        "services",
        "delivery-enabled",
        "delivery-enabled",
        "veg",
        "pair-with-bread",
        "home-style-meal",
        "services",
        "veg"
      ]
    },
    {
      "name": "Aloo Baingan",
      "description": "",
      "media": null,
      "price": 80,
      "menuName": "Main Course",
      "categoryName": "Veg Main Course",
      "slugs": [
        "veg",
        "home-style-meal",
        "services",
        "delivery-enabled",
        "delivery-enabled",
        "veg",
        "home-style-meal",
        "services",
        "veg"
      ]
    },
    {
      "name": "Chana Masala",
      "description": "",
      "media": null,
      "price": 90,
      "menuName": "Main Course",
      "categoryName": "Veg Main Course",
      "slugs": [
        "veg",
        "bestseller-lunch",
        "services",
        "delivery-enabled",
        "delivery-enabled",
        "veg",
        "bestseller-lunch",
        "services",
        "veg"
      ]
    },
    {
      "name": "Dal Fry",
      "description": "",
      "media": null,
      "price": 90,
      "menuName": "Main Course",
      "categoryName": "Veg Main Course",
      "slugs": [
        "veg",
        "services",
        "delivery-enabled",
        "delivery-enabled",
        "veg",
        "services",
        "veg"
      ]
    },
    {
      "name": "Dal Mughlai",
      "description": "",
      "media": null,
      "price": 90,
      "menuName": "Main Course",
      "categoryName": "Veg Main Course",
      "slugs": [
        "veg",
        "pair-with-bread",
        "home-style-meal",
        "services",
        "delivery-enabled",
        "delivery-enabled",
        "veg",
        "pair-with-bread",
        "home-style-meal",
        "services",
        "veg"
      ]
    },
    {
      "name": "Dal Tadka",
      "description": "",
      "media": null,
      "price": 90,
      "menuName": "Main Course",
      "categoryName": "Veg Main Course",
      "slugs": [
        "veg",
        "pair-with-bread",
        "services",
        "delivery-enabled",
        "delivery-enabled",
        "veg",
        "pair-with-bread",
        "services",
        "veg"
      ]
    },
    {
      "name": "Bhindi Masala",
      "description": "",
      "media": null,
      "price": 90,
      "menuName": "Main Course",
      "categoryName": "Veg Main Course",
      "slugs": [
        "veg",
        "pair-with-bread",
        "services",
        "delivery-enabled",
        "delivery-enabled",
        "veg",
        "pair-with-bread",
        "services",
        "veg"
      ]
    },
    {
      "name": "Chicken Masala",
      "description": "",
      "media": null,
      "price": 140,
      "menuName": "Main Course",
      "categoryName": "Chicken Main Course",
      "slugs": [
        "non-veg",
        "bestseller-lunch",
        "bestseller-evening",
        "bestseller-dinner",
        "bestseller-late-night",
        "pair-with-bread",
        "services",
        "delivery-enabled",
        "delivery-enabled",
        "non-veg",
        "bestseller-lunch",
        "bestseller-evening",
        "bestseller-dinner",
        "bestseller-late-night",
        "pair-with-bread",
        "services",
        "non-veg"
      ]
    },
    {
      "name": "Chicken Handi",
      "description": "",
      "media": "https://b.zmtcdn.com/data/dish_photos/b9e/0a5594a6ac95e1e5c544dbea6099cb9e.jpg",
      "price": 190,
      "menuName": "Main Course",
      "categoryName": "Chicken Main Course",
      "slugs": [
        "non-veg",
        "bestseller-lunch",
        "bestseller-evening",
        "bestseller-dinner",
        "bestseller-late-night",
        "hero-item",
        "services",
        "delivery-enabled",
        "delivery-enabled",
        "non-veg",
        "bestseller-lunch",
        "bestseller-evening",
        "bestseller-dinner",
        "bestseller-late-night",
        "hero-item",
        "services",
        "non-veg"
      ]
    },
    {
      "name": "Chicken Kadhai",
      "description": "",
      "media": null,
      "price": 180,
      "menuName": "Main Course",
      "categoryName": "Chicken Main Course",
      "slugs": [
        "non-veg",
        "bestseller-late-night",
        "services",
        "delivery-enabled",
        "delivery-enabled",
        "non-veg",
        "bestseller-late-night",
        "services",
        "non-veg"
      ]
    },
    {
      "name": "Chicken Green Masala",
      "description": "",
      "media": null,
      "price": 160,
      "menuName": "Main Course",
      "categoryName": "Chicken Main Course",
      "slugs": [
        "non-veg",
        "services",
        "delivery-enabled",
        "delivery-enabled",
        "non-veg",
        "services",
        "non-veg"
      ]
    },
    {
      "name": "Chicken Bombay",
      "description": "",
      "media": null,
      "price": 200,
      "menuName": "Main Course",
      "categoryName": "Chicken Main Course",
      "slugs": [
        "non-veg",
        "services",
        "delivery-enabled",
        "delivery-enabled",
        "non-veg",
        "services",
        "non-veg"
      ]
    },
    {
      "name": "Chicken Mughlai",
      "description": "",
      "media": "https://b.zmtcdn.com/data/dish_photos/f38/1d78550e09901fd1e931a733d56a2f38.jpg",
      "price": 190,
      "menuName": "Main Course",
      "categoryName": "Chicken Main Course",
      "slugs": [
        "non-veg",
        "bestseller-lunch",
        "bestseller-evening",
        "bestseller-dinner",
        "bestseller-late-night",
        "hero-item",
        "pair-with-bread",
        "services",
        "delivery-enabled",
        "delivery-enabled",
        "non-veg",
        "bestseller-lunch",
        "bestseller-evening",
        "bestseller-dinner",
        "bestseller-late-night",
        "hero-item",
        "pair-with-bread",
        "services",
        "non-veg"
      ]
    },
    {
      "name": "Chicken 65 Gravy",
      "description": "",
      "media": null,
      "price": 190,
      "menuName": "Main Course",
      "categoryName": "Chicken Main Course",
      "slugs": [
        "non-veg",
        "services",
        "delivery-enabled",
        "delivery-enabled",
        "non-veg",
        "services",
        "non-veg"
      ]
    },
    {
      "name": "Chicken Aazmi",
      "description": "",
      "media": null,
      "price": 180,
      "menuName": "Main Course",
      "categoryName": "Chicken Main Course",
      "slugs": [
        "non-veg",
        "services",
        "delivery-enabled",
        "delivery-enabled",
        "non-veg",
        "services",
        "non-veg"
      ]
    },
    {
      "name": "Chicken Lasania",
      "description": "",
      "media": null,
      "price": 180,
      "menuName": "Main Course",
      "categoryName": "Chicken Main Course",
      "slugs": [
        "non-veg",
        "services",
        "delivery-enabled",
        "delivery-enabled",
        "non-veg",
        "services",
        "non-veg"
      ]
    },
    {
      "name": "Chicken Angara",
      "description": "",
      "media": null,
      "price": 190,
      "menuName": "Main Course",
      "categoryName": "Chicken Main Course",
      "slugs": [
        "non-veg",
        "services",
        "delivery-enabled",
        "delivery-enabled",
        "non-veg",
        "services",
        "non-veg"
      ]
    },
    {
      "name": "Boneless Chicken",
      "description": "",
      "media": null,
      "price": 190,
      "menuName": "Main Course",
      "categoryName": "Chicken Main Course",
      "slugs": [
        "non-veg",
        "services",
        "delivery-enabled",
        "delivery-enabled",
        "non-veg",
        "services",
        "non-veg"
      ]
    },
    {
      "name": "Boneless Butter Chicken",
      "description": "",
      "media": "https://b.zmtcdn.com/data/dish_photos/5df/b68b55079350bea47d9728053663c5df.jpg",
      "price": 230,
      "menuName": "Main Course",
      "categoryName": "Chicken Main Course",
      "slugs": [
        "non-veg",
        "bestseller-lunch",
        "bestseller-evening",
        "bestseller-dinner",
        "bestseller-late-night",
        "pair-with-bread",
        "services",
        "delivery-enabled",
        "delivery-enabled",
        "non-veg",
        "bestseller-lunch",
        "bestseller-evening",
        "bestseller-dinner",
        "bestseller-late-night",
        "pair-with-bread",
        "services",
        "non-veg"
      ]
    },
    {
      "name": "Chicken Leg Masala",
      "description": "",
      "media": null,
      "price": 190,
      "menuName": "Main Course",
      "categoryName": "Chicken Main Course",
      "slugs": [
        "non-veg",
        "services",
        "delivery-enabled",
        "delivery-enabled",
        "non-veg",
        "services",
        "non-veg"
      ]
    },
    {
      "name": "Egg Masala",
      "description": "",
      "media": null,
      "price": 100,
      "menuName": "Main Course",
      "categoryName": "Egg Main Course",
      "slugs": [
        "egg",
        "services",
        "delivery-enabled",
        "delivery-enabled",
        "egg",
        "services",
        "egg"
      ]
    },
    {
      "name": "Egg Keema",
      "description": "",
      "media": null,
      "price": 100,
      "menuName": "Main Course",
      "categoryName": "Egg Main Course",
      "slugs": [
        "egg",
        "pair-with-bread",
        "services",
        "delivery-enabled",
        "delivery-enabled",
        "egg",
        "pair-with-bread",
        "services",
        "egg"
      ]
    },
    {
      "name": "Egg Bhurji",
      "description": "",
      "media": null,
      "price": 90,
      "menuName": "Main Course",
      "categoryName": "Egg Main Course",
      "slugs": [
        "egg",
        "services",
        "delivery-enabled",
        "delivery-enabled",
        "egg",
        "services",
        "egg"
      ]
    },
    {
      "name": "Fish Masala",
      "description": "",
      "media": null,
      "price": 160,
      "menuName": "Main Course",
      "categoryName": "Fish and Prawn",
      "slugs": [
        "non-veg",
        "bestseller-lunch",
        "services",
        "delivery-enabled",
        "delivery-enabled",
        "non-veg",
        "bestseller-lunch",
        "services",
        "non-veg"
      ]
    },
    {
      "name": "Chapati Roti",
      "description": "",
      "media": null,
      "price": 10,
      "menuName": "Breads",
      "categoryName": "",
      "slugs": [
        "veg",
        "reco-breads",
        "home-style-meal",
        "services",
        "delivery-enabled",
        "delivery-enabled",
        "veg",
        "reco-breads",
        "home-style-meal",
        "services",
        "veg"
      ]
    },
    {
      "name": "Butter Chapati Roti",
      "description": "",
      "media": null,
      "price": 12,
      "menuName": "Breads",
      "categoryName": "",
      "slugs": [
        "veg",
        "reco-breads",
        "bread",
        "home-style-meal",
        "services",
        "sf-not-vegan",
        "delivery-enabled",
        "delivery-enabled",
        "veg",
        "reco-breads",
        "bread",
        "home-style-meal",
        "services",
        "sf-not-vegan",
        "veg"
      ]
    },
    {
      "name": "Tandoori Roti",
      "description": "",
      "media": null,
      "price": 10,
      "menuName": "Breads",
      "categoryName": "",
      "slugs": [
        "veg",
        "reco-breads",
        "services",
        "delivery-enabled",
        "delivery-enabled",
        "veg",
        "reco-breads",
        "services",
        "veg"
      ]
    },
    {
      "name": "Butter Tandoori Roti",
      "description": "",
      "media": null,
      "price": 15,
      "menuName": "Breads",
      "categoryName": "",
      "slugs": [
        "veg",
        "reco-breads",
        "services",
        "sf-not-vegan",
        "delivery-enabled",
        "delivery-enabled",
        "veg",
        "reco-breads",
        "services",
        "sf-not-vegan",
        "veg"
      ]
    },
    {
      "name": "Plain Rice",
      "description": "",
      "media": null,
      "price": 100,
      "menuName": "Rice and Biryani",
      "categoryName": "Rice",
      "slugs": [
        "veg",
        "reco-rice",
        "home-style-meal",
        "services",
        "delivery-enabled",
        "delivery-enabled",
        "veg",
        "reco-rice",
        "home-style-meal",
        "services",
        "veg"
      ]
    },
    {
      "name": "Jeera Rice",
      "description": "",
      "media": null,
      "price": 110,
      "menuName": "Rice and Biryani",
      "categoryName": "Rice",
      "slugs": [
        "veg",
        "reco-rice",
        "bestseller-evening",
        "home-style-meal",
        "services",
        "delivery-enabled",
        "delivery-enabled",
        "veg",
        "reco-rice",
        "bestseller-evening",
        "home-style-meal",
        "services",
        "veg"
      ]
    },
    {
      "name": "Egg Puloa",
      "description": "",
      "media": null,
      "price": 110,
      "menuName": "Rice and Biryani",
      "categoryName": "Rice",
      "slugs": [
        "egg",
        "reco-rice",
        "services",
        "delivery-enabled",
        "delivery-enabled",
        "egg",
        "reco-rice",
        "services",
        "egg"
      ]
    },
    {
      "name": "Chicken Pulao",
      "description": "",
      "media": null,
      "price": 140,
      "menuName": "Rice and Biryani",
      "categoryName": "Rice",
      "slugs": [
        "non-veg",
        "reco-rice",
        "bestseller-evening",
        "bestseller-dinner",
        "services",
        "delivery-enabled",
        "delivery-enabled",
        "non-veg",
        "reco-rice",
        "bestseller-evening",
        "bestseller-dinner",
        "services",
        "non-veg"
      ]
    },
    {
      "name": "Chicken Biryani",
      "description": "",
      "media": "https://b.zmtcdn.com/data/dish_photos/7ec/982162ad7ebcf9b7db17728ce24e17ec.jpg",
      "price": 120,
      "menuName": "Rice and Biryani",
      "categoryName": "Biryani",
      "slugs": [
        "non-veg",
        "bestseller-lunch",
        "bestseller-evening",
        "bestseller-dinner",
        "bestseller-late-night",
        "restaurant-recommended",
        "hero-item",
        "services",
        "delivery-enabled",
        "delivery-enabled",
        "non-veg",
        "bestseller-lunch",
        "bestseller-evening",
        "bestseller-dinner",
        "bestseller-late-night",
        "restaurant-recommended",
        "hero-item",
        "services",
        "non-veg"
      ]
    },
    {
      "name": "Egg Omlet",
      "description": "",
      "media": null,
      "price": 100,
      "menuName": "Egg Omlet",
      "categoryName": "",
      "slugs": [
        "egg",
        "reco-snacks",
        "services",
        "delivery-enabled",
        "delivery-enabled",
        "egg",
        "reco-snacks",
        "services",
        "egg"
      ]
    }
  ]
}